fsm_assignments/problem3_vending/vending_mealy.v
module vending_mealy(
    input wire clk,
    input wire rst,       // sync active-high reset
    input wire [1:0] coin, // 01=5, 10=10, 00=idle (ignore 11)
    output reg dispense,   // 1-cycle pulse when total >= 20
    output reg chg5        // 1-cycle pulse when total=25
);

    parameter S0  = 3'b000,  // 0
              S5  = 3'b001,  // 5
              S10 = 3'b010,  // 10
              S15 = 3'b011,  // 15
              S20 = 3'b100;  // 20 (dispense here)
        
    reg [2:0] state, next_state;
    wire coin5  = (coin == 2'b01);  // 5 coin
    wire coin10 = (coin == 2'b10);  // 10 coin
    always @(*) begin
        next_state = state;
        dispense = 1'b0;
        chg5 = 1'b0;

        case(state)
            S0: begin
                if (coin5)       next_state = S5;
                else if (coin10) next_state = S10;
            end
            S5: begin
                if (coin5)       next_state = S10;
                else if (coin10) next_state = S15;
            end
            S10: begin
                if (coin5)       next_state = S15;
                else if (coin10) next_state = S20;
            end
            S15: begin
                if (coin5)       next_state = S20;
                else if (coin10) begin
                    next_state = S0;
                    dispense = 1'b1;  
                    chg5 = 1'b1;
                end
            end
            S20: begin
                next_state = S0;
                dispense = 1'b1;  
            end
        endcase
    end


    always @(posedge clk) begin
        if (rst) state <= S0;
        else state <= next_state;
    end

endmodule

fsm_assignments/problem3_vending/tb_vending_mealy.v
module tb_vending_mealy;
    reg clk, rst;
    reg [1:0] coin;
    wire dispense, chg5;

    vending_mealy dut (.*);

    // Clock (100MHz)
    always #5 clk = ~clk;

    initial begin
        clk = 0; rst = 1;
        coin = 0;
        #20 rst = 0;

    
        #10 coin = 2'b01; // 5
        #10 coin = 2'b01; // 5
        #10 coin = 2'b10; // 10 (total=20)
        #10 coin = 0;

        #20 coin = 2'b10; 
        #10 coin = 2'b10; 
        #10 coin = 0;

    
        #20 coin = 2'b01; // 5
        #10 coin = 2'b10; // 10
        #10 coin = 2'b10; // 10 (total=25)
        #10 coin = 0;

        #20 $finish;
    end

    initial begin
        $dumpfile("dump.vcd");
        $dumpvars(0, tb_vending_mealy);
       
    end
endmodule

fsm_assignments/problem3_vending/dump.vcd
$date
	Tue Aug 19 07:56:40 2025
$end
$version
	Icarus Verilog
$end
$timescale
	1s
$end
$scope module tb_vending_mealy $end
$var wire 1 ! dispense $end
$var wire 1 " chg5 $end
$var reg 1 # clk $end
$var reg 2 $ coin [1:0] $end
$var reg 1 % rst $end
$scope module dut $end
$var wire 1 # clk $end
$var wire 2 & coin [1:0] $end
$var wire 1 % rst $end
$var wire 1 ' coin5 $end
$var wire 1 ( coin10 $end
$var parameter 3 ) S0 $end
$var parameter 3 * S10 $end
$var parameter 3 + S15 $end
$var parameter 3 , S20 $end
$var parameter 3 - S5 $end
$var reg 1 " chg5 $end
$var reg 1 ! dispense $end
$var reg 3 . next_state [2:0] $end
$var reg 3 / state [2:0] $end
$upscope $end
$upscope $end
$enddefinitions $end
$comment Show the parameter values. $end
$dumpall
b1 -
b100 ,
b11 +
b10 *
b0 )
$end
#0
$dumpvars
bx /
bx .
0(
0'
b0 &
1%
b0 $
0#
0"
0!
$end
#5
b0 .
b0 /
1#
#10
0#
#15
1#
#20
0#
0%
#25
1#
#30
b1 .
0#
1'
b1 $
b1 &
#35
b10 .
b1 /
1#
#40
0#
#45
b11 .
b10 /
1#
#50
b100 .
0#
0'
1(
b10 $
b10 &
#55
1!
b0 .
b100 /
1#
#60
1!
b0 .
0#
0(
b0 $
b0 &
#65
0!
b0 /
1#
#70
0#
#75
1#
#80
b10 .
0#
1(
b10 $
b10 &
#85
b100 .
b10 /
1#
#90
0#
#95
1!
b0 .
b100 /
1#
#100
1!
b0 .
0#
0(
b0 $
b0 &
#105
0!
b0 /
1#
#110
0#
#115
1#
#120
b1 .
0#
1'
b1 $
b1 &
#125
b10 .
b1 /
1#
#130
b11 .
0#
0'
1(
b10 $
b10 &
#135
1"
1!
b0 .
b11 /
1#
#140
0#
#145
b10 .
0"
0!
b0 /
1#
#150
b0 .
0#
0(
b0 $
b0 &
