fsm_assignments/problem1_seqdet/seq_detect_mealy.v
module seq_detect_mealy(
  input  wire clk,
  input  wire rst,   // sync active-high
  input  wire din,   // serial input bit per clock
  output wire y      // 1-cycle pulse when ...1101 seen
);

  
  parameter s0 = 2'b00,
            s1 = 2'b01,
            s2 = 2'b10,
            s3 = 2'b11;

  reg [1:0] state, next_state;

  
  always @(*) begin
    case (state)
      s0: next_state = din ? s1 : s0;
      s1: next_state = din ? s2 : s0;
      s2: next_state = din ? s2 : s3;
      s3: next_state = din ? s1 : s0;
      default: next_state = s0;
    endcase
  end

  
  always @(posedge clk) begin
    if (rst)
      state <= s0;
    else
      state <= next_state;
  end

  
  assign y = (state == s3) && din;

endmodule

fsm_assignments/problem1_seqdet/tb_seq_detect_mealy.v
`timescale 1ns/1ps
module tb_seq_detect_mealy;
  reg clk=0, rst=1, din=0;
  wire y;

  seq_detect_mealy dut(.clk(clk), .rst(rst), .din(din), .y(y));

  always #5 clk = ~clk;  // 10ns period

 
  reg [10:0] stream = 11'b11011011101;
  integer i;

  initial begin
    $dumpfile("dump.vcd");
    $dumpvars(0, tb_seq_detect_mealy);

   
    repeat (3) @(posedge clk);
    rst = 0;

    
    for (i = 10; i >= 0; i=i-1) begin
      din = stream[i];
      @(posedge clk);
      #1;
      if (y) $display("t=%0t ns: DETECT at index %0d", $time, 10-i);
    end

    repeat (5) @(posedge clk);
    $finish;
  end
endmodule

fsm_assignments/problem1_seqdet/dump.vcd
$date
	Tue Aug 19 06:47:28 2025
$end
$version
	Icarus Verilog
$end
$timescale
	1ps
$end
$scope module tb_seq_detect_mealy $end
$var wire 1 ! y $end
$var reg 1 " clk $end
$var reg 1 # din $end
$var reg 1 $ rst $end
$var reg 11 % stream [10:0] $end
$var integer 32 & i [31:0] $end
$scope module dut $end
$var wire 1 " clk $end
$var wire 1 # din $end
$var wire 1 $ rst $end
$var wire 1 ! y $end
$var parameter 2 ' s0 $end
$var parameter 2 ( s1 $end
$var parameter 2 ) s2 $end
$var parameter 2 * s3 $end
$var reg 2 + next_state [1:0] $end
$var reg 2 , state [1:0] $end
$upscope $end
$upscope $end
$enddefinitions $end
$comment Show the parameter values. $end
$dumpall
b11 *
b10 )
b1 (
b0 '
$end
#0
$dumpvars
bx ,
b0 +
bx &
b11011011101 %
1$
0#
0"
0!
$end
#5000
b0 ,
1"
#10000
0"
#15000
1"
#20000
0"
#25000
b1 +
1#
b1010 &
0$
1"
#30000
0"
#35000
b10 +
b1 ,
1"
#36000
b1001 &
#40000
0"
#45000
b10 ,
1"
#46000
b11 +
0#
b1000 &
#50000
0"
#55000
b0 +
b11 ,
1"
#56000
1!
b1 +
1#
b111 &
#60000
0"
#65000
b10 +
0!
b1 ,
1"
#66000
b110 &
#70000
0"
#75000
b10 ,
1"
#76000
b11 +
0#
b101 &
#80000
0"
#85000
b0 +
b11 ,
1"
#86000
1!
b1 +
1#
b100 &
#90000
0"
#95000
b10 +
0!
b1 ,
1"
#96000
b11 &
#100000
0"
#105000
b10 ,
1"
#106000
b10 &
#110000
0"
#115000
1"
#116000
b11 +
0#
b1 &
#120000
0"
#125000
b0 +
b11 ,
1"
#126000
1!
b1 +
1#
b0 &
#130000
0"
#135000
b10 +
0!
b1 ,
1"
#136000
b11111111111111111111111111111111 &
#140000
0"
#145000
b10 ,
1"
