fsm_assignments/problem4_link/slave_fsm.v
module slave_fsm(
    input wire clk,
    input wire rst,
    input wire req,
    input wire [7:0] data,
    output reg ack
);


    parameter [1:0] IDLE = 2'b00,
                   LATCH = 2'b01,
                   HOLD_ACK = 2'b10,
                   WAIT_REQ = 2'b11;
    
    reg [1:0] state, next_state;
    reg [1:0] hold_counter;
    reg [7:0] latched_data;
    
    
    always @(*) begin
        next_state = state;
        case (state)
            IDLE: if (req) next_state = LATCH;
            LATCH: next_state = HOLD_ACK;
            HOLD_ACK: begin
                if (hold_counter == 1) next_state = WAIT_REQ;
            end
            WAIT_REQ: if (~req) next_state = IDLE;
        endcase
    end
    

    always @(posedge clk) begin
        if (rst) begin
            state <= IDLE;
            ack <= 0;
            hold_counter <= 0;
            latched_data <= 0;
        end
        else begin
            state <= next_state;
            
            case (state)
                IDLE: begin
                    ack <= 0;
                    hold_counter <= 0;
                end
                LATCH: begin
                    latched_data <= data;
                    ack <= 1;
                end
                HOLD_ACK: begin
                    hold_counter <= hold_counter + 1;
                end
                WAIT_REQ: begin
                    ack <= 0;
                    hold_counter <= 0;
                end
            endcase
        end
    end

endmodule

fsm_assignments/problem4_link/master_fsm.v
module master_fsm(
    input wire clk,
    input wire rst,
    input wire ack,
    output reg req,
    output reg [7:0] data,
    output reg done
);

    
    parameter [1:0] IDLE = 2'b00,
                   SEND = 2'b01,
                   WAIT_ACK = 2'b10,
                   COMPLETE = 2'b11;
    
    reg [1:0] state, next_state;
    reg [1:0] byte_count;
    reg [7:0] data_values [0:3]; 
    
    
    initial begin
        data_values[0] = 8'hA5;
        data_values[1] = 8'h3C;
        data_values[2] = 8'h7E;
        data_values[3] = 8'hD9;
    end
    
    
    always @(*) begin
        next_state = state;
        case (state)
            IDLE: next_state = SEND;
            SEND: next_state = WAIT_ACK;
            WAIT_ACK: begin
                if (ack) next_state = (byte_count == 3) ? COMPLETE : SEND;
            end
            COMPLETE: next_state = IDLE;
        endcase
    end
    
    
    always @(posedge clk) begin
        if (rst) begin
            state <= IDLE;
            byte_count <= 0;
            req <= 0;
            done <= 0;
            data <= 0;
        end
        else begin
            state <= next_state;
            
            case (state)
                IDLE: begin
                    byte_count <= 0;
                    done <= 0;
                end
                SEND: begin
                    req <= 1;
                    data <= data_values[byte_count];
                end
                WAIT_ACK: begin
                    if (ack) begin
                        req <= 0;
                        byte_count <= byte_count + 1;
                    end
                end
                COMPLETE: begin
                    done <= 1;
                end
            endcase
        end
    end

endmodule

fsm_assignments/problem4_link/link_top.v
module link_top(
    input wire clk,
    input wire rst,
    output wire done
);

    wire req, ack;
    wire [7:0] data;
    
    master_fsm master (
        .clk(clk),
        .rst(rst),
        .ack(ack),
        .req(req),
        .data(data),
        .done(done)
    );
    
    slave_fsm slave (
        .clk(clk),
        .rst(rst),
        .req(req),
        .data(data),
        .ack(ack)
    );

endmodule

fsm_assignments/problem4_link/tb_link_top.v
module tb_link_top;
    reg clk, rst;
    wire done;
    
    link_top dut(.clk(clk), .rst(rst), .done(done));
    
    // Clock generation (100 MHz)
    initial begin
        clk = 0;
        forever #5 clk = ~clk;
    end
    
    
    initial begin
        rst = 1;
        #20 rst = 0;
    end
    
   
    initial begin
        wait(done == 1);
        #20 $finish;
    end
    
 
    initial begin
        $dumpfile("dump.vcd");
        $dumpvars(0, tb_link_top);
    end
    

    always @(posedge clk) begin
        $display("Time=%0t: req=%b, ack=%b, data=%h, done=%b",
                $time, dut.master.req, dut.slave.ack, dut.master.data, done);
    end

endmodule

fsm_assignments/problem4_link/dump.vcd
$date
	Tue Aug 19 00:54:47 2025
$end
$version
	Icarus Verilog
$end
$timescale
	1s
$end
$scope module tb_link_top $end
$var wire 1 ! done $end
$var reg 1 " clk $end
$var reg 1 # rst $end
$scope module dut $end
$var wire 1 " clk $end
$var wire 1 # rst $end
$var wire 1 $ req $end
$var wire 1 ! done $end
$var wire 8 % data [7:0] $end
$var wire 1 & ack $end
$scope module master $end
$var wire 1 " clk $end
$var wire 1 # rst $end
$var wire 1 & ack $end
$var parameter 2 ' COMPLETE $end
$var parameter 2 ( IDLE $end
$var parameter 2 ) SEND $end
$var parameter 2 * WAIT_ACK $end
$var reg 2 + byte_count [1:0] $end
$var reg 8 , data [7:0] $end
$var reg 1 ! done $end
$var reg 2 - next_state [1:0] $end
$var reg 1 $ req $end
$var reg 2 . state [1:0] $end
$upscope $end
$scope module slave $end
$var wire 1 " clk $end
$var wire 8 / data [7:0] $end
$var wire 1 $ req $end
$var wire 1 # rst $end
$var parameter 2 0 HOLD_ACK $end
$var parameter 2 1 IDLE $end
$var parameter 2 2 LATCH $end
$var parameter 2 3 WAIT_REQ $end
$var reg 1 & ack $end
$var reg 2 4 hold_counter [1:0] $end
$var reg 8 5 latched_data [7:0] $end
$var reg 2 6 next_state [1:0] $end
$var reg 2 7 state [1:0] $end
$upscope $end
$upscope $end
$upscope $end
$enddefinitions $end
$comment Show the parameter values. $end
$dumpall
b11 3
b1 2
b0 1
b10 0
b10 *
b1 )
b0 (
b11 '
$end
#0
$dumpvars
bx 7
bx 6
bx 5
bx 4
bx /
bx .
bx -
bx ,
bx +
x&
bx %
x$
1#
0"
x!
$end
#5
b1 -
b0 6
b0 %
b0 ,
b0 /
0!
0$
b0 +
b0 .
b0 5
b0 4
0&
b0 7
1"
#10
0"
#15
1"
#20
0"
0#
#25
b10 -
b1 .
1"
#30
0"
#35
b1 6
b10100101 %
b10100101 ,
b10100101 /
1$
b10 .
1"
#40
0"
#45
b10 6
b1 7
1"
#50
0"
#55
b1 -
1&
b10100101 5
b10 7
1"
#60
0"
#65
b10 -
b11 6
b1 +
0$
b1 .
b1 4
1"
#70
0"
#75
b1 -
b10 4
b11 7
b111100 %
b111100 ,
b111100 /
1$
b10 .
1"
#80
0"
#85
b0 6
b10 -
b10 +
0$
b1 .
b0 4
0&
1"
#90
0"
#95
b1 6
b0 7
b1111110 %
b1111110 ,
b1111110 /
1$
b10 .
1"
#100
0"
#105
b10 6
b1 7
1"
#110
0"
#115
b1 -
1&
b1111110 5
b10 7
1"
#120
0"
#125
b10 -
b11 6
b11 +
0$
b1 .
b1 4
1"
#130
0"
#135
b11 -
b10 4
b11 7
b11011001 %
b11011001 ,
b11011001 /
1$
b10 .
1"
#140
0"
#145
b0 6
b0 -
b0 +
0$
b11 .
b0 4
0&
1"
#150
0"
#155
b1 -
b0 7
1!
b0 .
1"
#160
0"
#165
b10 -
0!
b1 .
1"
#170
0"
#175
b1 6
b10100101 %
b10100101 ,
b10100101 /
1$
b10 .
1"
